{
  "generatedAt": "2026-03-15T09:36:23.634837Z",
  "totalRooms": 4509,
  "signalCounts": {
    "STRONG_PUT": 431,
    "PUT": 275,
    "WATCH": 252,
    "NEUTRAL": 3551
  },
  "putRate": 15.7,
  "description": "Next-scan price drop prediction. PUT = expected ≥5% drop in the next 3-hour scan cycle.",
  "topSignals": [
    {
      "detailId": 39801,
      "hotelId": 24982,
      "hotelName": "Hilton Miami Downtown",
      "category": "Suite",
      "board": "Ro",
      "currentPrice": 254.52,
      "signal": "STRONG_PUT",
      "strength": 10,
      "probability": 1.0,
      "expectedDropPct": -25.92,
      "features": {
        "velocity3h": -25.923,
        "acceleration": -1.0,
        "dropFrequency": 1.0,
        "consecutiveDrops": 3,
        "maxSingleDropPct": 349.54,
        "marketPressure": 0.0,
        "totalScans": 4,
        "totalDrops": 3
      },
      "daysToCheckin": 101
    },
    {
      "detailId": 39116,
      "hotelId": 24982,
      "hotelName": "Hilton Miami Downtown",
      "category": "Suite",
      "board": "Ro",
      "currentPrice": 1144.95,
      "signal": "STRONG_PUT",
      "strength": 10,
      "probability": 1.0,
      "expectedDropPct": -25.92,
      "features": {
        "velocity3h": -25.923,
        "acceleration": -1.0,
        "dropFrequency": 1.0,
        "consecutiveDrops": 3,
        "maxSingleDropPct": 77.7,
        "marketPressure": 0.0,
        "totalScans": 4,
        "totalDrops": 3
      },
      "daysToCheckin": 101
    },
    {
      "detailId": 39351,
      "hotelId": 24982,
      "hotelName": "Hilton Miami Downtown",
      "category": "Suite",
      "board": "Ro",
      "currentPrice": 1144.86,
      "signal": "STRONG_PUT",
      "strength": 10,
      "probability": 1.0,
      "expectedDropPct": -25.92,
      "features": {
        "velocity3h": -25.923,
        "acceleration": -1.0,
        "dropFrequency": 1.0,
        "consecutiveDrops": 3,
        "maxSingleDropPct": 77.71,
        "marketPressure": 0.0,
        "totalScans": 4,
        "totalDrops": 3
      },
      "daysToCheckin": 101
    },
    {
      "detailId": 39622,
      "hotelId": 24982,
      "hotelName": "Hilton Miami Downtown",
      "category": "Suite",
      "board": "Ro",
      "currentPrice": 1144.16,
      "signal": "STRONG_PUT",
      "strength": 10,
      "probability": 1.0,
      "expectedDropPct": -25.92,
      "features": {
        "velocity3h": -25.923,
        "acceleration": -1.0,
        "dropFrequency": 1.0,
        "consecutiveDrops": 3,
        "maxSingleDropPct": 77.75,
        "marketPressure": 0.0,
        "totalScans": 4,
        "totalDrops": 3
      },
      "daysToCheckin": 101
    },
    {
      "detailId": 39825,
      "hotelId": 24982,
      "hotelName": "Hilton Miami Downtown",
      "category": "Suite",
      "board": "Ro",
      "currentPrice": 254.53,
      "signal": "STRONG_PUT",
      "strength": 10,
      "probability": 1.0,
      "expectedDropPct": -19.43,
      "features": {
        "velocity3h": -19.433,
        "acceleration": -1.0,
        "dropFrequency": 1.0,
        "consecutiveDrops": 3,
        "maxSingleDropPct": 347.14,
        "marketPressure": 0.0,
        "totalScans": 5,
        "totalDrops": 3
      },
      "daysToCheckin": 107
    },
    {
      "detailId": 39798,
      "hotelId": 24982,
      "hotelName": "Hilton Miami Downtown",
      "category": "Suite",
      "board": "Ro",
      "currentPrice": 1138.1,
      "signal": "STRONG_PUT",
      "strength": 10,
      "probability": 1.0,
      "expectedDropPct": -19.43,
      "features": {
        "velocity3h": -19.433,
        "acceleration": -1.0,
        "dropFrequency": 1.0,
        "consecutiveDrops": 3,
        "maxSingleDropPct": 77.64,
        "marketPressure": 0.0,
        "totalScans": 5,
        "totalDrops": 3
      },
      "daysToCheckin": 107
    },
    {
      "detailId": 39089,
      "hotelId": 24982,
      "hotelName": "Hilton Miami Downtown",
      "category": "Suite",
      "board": "Ro",
      "currentPrice": 1142.71,
      "signal": "STRONG_PUT",
      "strength": 10,
      "probability": 1.0,
      "expectedDropPct": -19.43,
      "features": {
        "velocity3h": -19.433,
        "acceleration": -1.0,
        "dropFrequency": 1.0,
        "consecutiveDrops": 3,
        "maxSingleDropPct": 77.32,
        "marketPressure": 0.0,
        "totalScans": 5,
        "totalDrops": 3
      },
      "daysToCheckin": 107
    },
    {
      "detailId": 39117,
      "hotelId": 24982,
      "hotelName": "Hilton Miami Downtown",
      "category": "Suite",
      "board": "Ro",
      "currentPrice": 1142.71,
      "signal": "STRONG_PUT",
      "strength": 10,
      "probability": 1.0,
      "expectedDropPct": -19.43,
      "features": {
        "velocity3h": -19.433,
        "acceleration": -1.0,
        "dropFrequency": 1.0,
        "consecutiveDrops": 3,
        "maxSingleDropPct": 77.32,
        "marketPressure": 0.0,
        "totalScans": 5,
        "totalDrops": 3
      },
      "daysToCheckin": 107
    },
    {
      "detailId": 39657,
      "hotelId": 24982,
      "hotelName": "Hilton Miami Downtown",
      "category": "Suite",
      "board": "Ro",
      "currentPrice": 1141.93,
      "signal": "STRONG_PUT",
      "strength": 10,
      "probability": 1.0,
      "expectedDropPct": -19.43,
      "features": {
        "velocity3h": -19.433,
        "acceleration": -1.0,
        "dropFrequency": 1.0,
        "consecutiveDrops": 3,
        "maxSingleDropPct": 77.38,
        "marketPressure": 0.0,
        "totalScans": 5,
        "totalDrops": 3
      },
      "daysToCheckin": 107
    },
    {
      "detailId": 38889,
      "hotelId": 20702,
      "hotelName": "Embassy Suites by Hilton Miami International Airport",
      "category": "Suite",
      "board": "Ro",
      "currentPrice": 368.76,
      "signal": "STRONG_PUT",
      "strength": 10,
      "probability": 1.0,
      "expectedDropPct": -15.73,
      "features": {
        "velocity3h": -15.73,
        "acceleration": -1.0,
        "dropFrequency": 1.0,
        "consecutiveDrops": 3,
        "maxSingleDropPct": 41.59,
        "marketPressure": 0.0,
        "totalScans": 4,
        "totalDrops": 3
      },
      "daysToCheckin": 53
    },
    {
      "detailId": 39031,
      "hotelId": 20702,
      "hotelName": "Embassy Suites by Hilton Miami International Airport",
      "category": "Suite",
      "board": "Ro",
      "currentPrice": 349.95,
      "signal": "STRONG_PUT",
      "strength": 10,
      "probability": 1.0,
      "expectedDropPct": -15.73,
      "features": {
        "velocity3h": -15.73,
        "acceleration": -1.0,
        "dropFrequency": 1.0,
        "consecutiveDrops": 3,
        "maxSingleDropPct": 43.82,
        "marketPressure": 0.0,
        "totalScans": 4,
        "totalDrops": 3
      },
      "daysToCheckin": 53
    },
    {
      "detailId": 39376,
      "hotelId": 20702,
      "hotelName": "Embassy Suites by Hilton Miami International Airport",
      "category": "Suite",
      "board": "Ro",
      "currentPrice": 348.12,
      "signal": "STRONG_PUT",
      "strength": 10,
      "probability": 1.0,
      "expectedDropPct": -15.73,
      "features": {
        "velocity3h": -15.73,
        "acceleration": -1.0,
        "dropFrequency": 1.0,
        "consecutiveDrops": 3,
        "maxSingleDropPct": 44.05,
        "marketPressure": 0.0,
        "totalScans": 4,
        "totalDrops": 3
      },
      "daysToCheckin": 53
    },
    {
      "detailId": 39888,
      "hotelId": 20702,
      "hotelName": "Embassy Suites by Hilton Miami International Airport",
      "category": "Suite",
      "board": "Ro",
      "currentPrice": 194.76,
      "signal": "STRONG_PUT",
      "strength": 10,
      "probability": 1.0,
      "expectedDropPct": -15.73,
      "features": {
        "velocity3h": -15.73,
        "acceleration": -1.0,
        "dropFrequency": 1.0,
        "consecutiveDrops": 3,
        "maxSingleDropPct": 78.74,
        "marketPressure": 0.0,
        "totalScans": 4,
        "totalDrops": 3
      },
      "daysToCheckin": 53
    },
    {
      "detailId": 39772,
      "hotelId": 20702,
      "hotelName": "Embassy Suites by Hilton Miami International Airport",
      "category": "Suite",
      "board": "Ro",
      "currentPrice": 199.65,
      "signal": "STRONG_PUT",
      "strength": 10,
      "probability": 1.0,
      "expectedDropPct": -9.49,
      "features": {
        "velocity3h": -9.486,
        "acceleration": -1.0,
        "dropFrequency": 0.6,
        "consecutiveDrops": 3,
        "maxSingleDropPct": 93.7,
        "marketPressure": 0.0,
        "totalScans": 6,
        "totalDrops": 3
      },
      "daysToCheckin": 60
    },
    {
      "detailId": 39099,
      "hotelId": 20702,
      "hotelName": "Embassy Suites by Hilton Miami International Airport",
      "category": "Suite",
      "board": "Ro",
      "currentPrice": 425.79,
      "signal": "STRONG_PUT",
      "strength": 10,
      "probability": 1.0,
      "expectedDropPct": -9.49,
      "features": {
        "velocity3h": -9.486,
        "acceleration": -1.0,
        "dropFrequency": 0.6,
        "consecutiveDrops": 3,
        "maxSingleDropPct": 43.93,
        "marketPressure": 0.0,
        "totalScans": 6,
        "totalDrops": 3
      },
      "daysToCheckin": 60
    },
    {
      "detailId": 39377,
      "hotelId": 20702,
      "hotelName": "Embassy Suites by Hilton Miami International Airport",
      "category": "Suite",
      "board": "Ro",
      "currentPrice": 394.57,
      "signal": "STRONG_PUT",
      "strength": 10,
      "probability": 1.0,
      "expectedDropPct": -9.49,
      "features": {
        "velocity3h": -9.486,
        "acceleration": -1.0,
        "dropFrequency": 0.6,
        "consecutiveDrops": 3,
        "maxSingleDropPct": 47.41,
        "marketPressure": 0.0,
        "totalScans": 6,
        "totalDrops": 3
      },
      "daysToCheckin": 60
    },
    {
      "detailId": 39018,
      "hotelId": 20702,
      "hotelName": "Embassy Suites by Hilton Miami International Airport",
      "category": "Suite",
      "board": "Ro",
      "currentPrice": 390.54,
      "signal": "STRONG_PUT",
      "strength": 10,
      "probability": 1.0,
      "expectedDropPct": -9.49,
      "features": {
        "velocity3h": -9.486,
        "acceleration": -1.0,
        "dropFrequency": 0.6,
        "consecutiveDrops": 3,
        "maxSingleDropPct": 47.9,
        "marketPressure": 0.0,
        "totalScans": 6,
        "totalDrops": 3
      },
      "daysToCheckin": 60
    },
    {
      "detailId": 39634,
      "hotelId": 20702,
      "hotelName": "Embassy Suites by Hilton Miami International Airport",
      "category": "Suite",
      "board": "Ro",
      "currentPrice": 386.72,
      "signal": "STRONG_PUT",
      "strength": 10,
      "probability": 1.0,
      "expectedDropPct": -9.49,
      "features": {
        "velocity3h": -9.486,
        "acceleration": -1.0,
        "dropFrequency": 0.6,
        "consecutiveDrops": 3,
        "maxSingleDropPct": 48.37,
        "marketPressure": 0.0,
        "totalScans": 6,
        "totalDrops": 3
      },
      "daysToCheckin": 60
    },
    {
      "detailId": 38901,
      "hotelId": 20702,
      "hotelName": "Embassy Suites by Hilton Miami International Airport",
      "category": "Suite",
      "board": "Ro",
      "currentPrice": 379.77,
      "signal": "STRONG_PUT",
      "strength": 10,
      "probability": 1.0,
      "expectedDropPct": -9.49,
      "features": {
        "velocity3h": -9.486,
        "acceleration": -1.0,
        "dropFrequency": 0.6,
        "consecutiveDrops": 3,
        "maxSingleDropPct": 49.26,
        "marketPressure": 0.0,
        "totalScans": 6,
        "totalDrops": 3
      },
      "daysToCheckin": 60
    },
    {
      "detailId": 42921,
      "hotelId": 24982,
      "hotelName": "Hilton Miami Downtown",
      "category": "Suite",
      "board": "Ro",
      "currentPrice": 408.98,
      "signal": "STRONG_PUT",
      "strength": 10,
      "probability": 1.0,
      "expectedDropPct": -7.8,
      "features": {
        "velocity3h": -7.805,
        "acceleration": -1.0,
        "dropFrequency": 1.0,
        "consecutiveDrops": 2,
        "maxSingleDropPct": 18.49,
        "marketPressure": -0.5024,
        "totalScans": 3,
        "totalDrops": 2
      },
      "daysToCheckin": 36
    },
    {
      "detailId": 39807,
      "hotelId": 66814,
      "hotelName": "Breakwater South Beach",
      "category": "Deluxe",
      "board": "Ro",
      "currentPrice": 509.33,
      "signal": "STRONG_PUT",
      "strength": 10,
      "probability": 1.0,
      "expectedDropPct": -5.59,
      "features": {
        "velocity3h": -5.588,
        "acceleration": -1.0,
        "dropFrequency": 0.75,
        "consecutiveDrops": 3,
        "maxSingleDropPct": 22.7,
        "marketPressure": 0.0,
        "totalScans": 5,
        "totalDrops": 3
      },
      "daysToCheckin": 47
    },
    {
      "detailId": 39875,
      "hotelId": 66814,
      "hotelName": "Breakwater South Beach",
      "category": "Deluxe",
      "board": "Ro",
      "currentPrice": 509.33,
      "signal": "STRONG_PUT",
      "strength": 10,
      "probability": 1.0,
      "expectedDropPct": -5.59,
      "features": {
        "velocity3h": -5.588,
        "acceleration": -1.0,
        "dropFrequency": 0.75,
        "consecutiveDrops": 3,
        "maxSingleDropPct": 22.7,
        "marketPressure": 0.0,
        "totalScans": 5,
        "totalDrops": 3
      },
      "daysToCheckin": 47
    },
    {
      "detailId": 39848,
      "hotelId": 66814,
      "hotelName": "Breakwater South Beach",
      "category": "Deluxe",
      "board": "Ro",
      "currentPrice": 593.21,
      "signal": "STRONG_PUT",
      "strength": 10,
      "probability": 1.0,
      "expectedDropPct": -5.59,
      "features": {
        "velocity3h": -5.588,
        "acceleration": -1.0,
        "dropFrequency": 0.75,
        "consecutiveDrops": 3,
        "maxSingleDropPct": 19.49,
        "marketPressure": 0.0,
        "totalScans": 5,
        "totalDrops": 3
      },
      "daysToCheckin": 47
    },
    {
      "detailId": 39662,
      "hotelId": 66814,
      "hotelName": "Breakwater South Beach",
      "category": "Deluxe",
      "board": "Ro",
      "currentPrice": 624.94,
      "signal": "STRONG_PUT",
      "strength": 10,
      "probability": 1.0,
      "expectedDropPct": -5.59,
      "features": {
        "velocity3h": -5.588,
        "acceleration": -1.0,
        "dropFrequency": 0.75,
        "consecutiveDrops": 3,
        "maxSingleDropPct": 18.5,
        "marketPressure": 0.0,
        "totalScans": 5,
        "totalDrops": 3
      },
      "daysToCheckin": 47
    },
    {
      "detailId": 42134,
      "hotelId": 66814,
      "hotelName": "Breakwater South Beach",
      "category": "Deluxe",
      "board": "Ro",
      "currentPrice": 485.27,
      "signal": "STRONG_PUT",
      "strength": 10,
      "probability": 1.0,
      "expectedDropPct": -5.59,
      "features": {
        "velocity3h": -5.588,
        "acceleration": -1.0,
        "dropFrequency": 0.75,
        "consecutiveDrops": 3,
        "maxSingleDropPct": 23.82,
        "marketPressure": 0.0,
        "totalScans": 5,
        "totalDrops": 3
      },
      "daysToCheckin": 47
    },
    {
      "detailId": 39819,
      "hotelId": 24982,
      "hotelName": "Hilton Miami Downtown",
      "category": "Suite",
      "board": "Ro",
      "currentPrice": 254.53,
      "signal": "STRONG_PUT",
      "strength": 9,
      "probability": 0.95,
      "expectedDropPct": -38.88,
      "features": {
        "velocity3h": -38.875,
        "acceleration": -1.0,
        "dropFrequency": 1.0,
        "consecutiveDrops": 2,
        "maxSingleDropPct": 346.84,
        "marketPressure": 0.0,
        "totalScans": 3,
        "totalDrops": 2
      },
      "daysToCheckin": 98
    },
    {
      "detailId": 39350,
      "hotelId": 24982,
      "hotelName": "Hilton Miami Downtown",
      "category": "Suite",
      "board": "Ro",
      "currentPrice": 1143.75,
      "signal": "STRONG_PUT",
      "strength": 9,
      "probability": 0.95,
      "expectedDropPct": -38.88,
      "features": {
        "velocity3h": -38.875,
        "acceleration": -1.0,
        "dropFrequency": 1.0,
        "consecutiveDrops": 2,
        "maxSingleDropPct": 77.19,
        "marketPressure": 0.0,
        "totalScans": 3,
        "totalDrops": 2
      },
      "daysToCheckin": 98
    },
    {
      "detailId": 39771,
      "hotelId": 24982,
      "hotelName": "Hilton Miami Downtown",
      "category": "Suite",
      "board": "Ro",
      "currentPrice": 1137.34,
      "signal": "STRONG_PUT",
      "strength": 9,
      "probability": 0.95,
      "expectedDropPct": -38.88,
      "features": {
        "velocity3h": -38.875,
        "acceleration": -1.0,
        "dropFrequency": 1.0,
        "consecutiveDrops": 2,
        "maxSingleDropPct": 77.62,
        "marketPressure": 0.0,
        "totalScans": 3,
        "totalDrops": 2
      },
      "daysToCheckin": 98
    },
    {
      "detailId": 39037,
      "hotelId": 20702,
      "hotelName": "Embassy Suites by Hilton Miami International Airport",
      "category": "Suite",
      "board": "Ro",
      "currentPrice": 291.57,
      "signal": "STRONG_PUT",
      "strength": 9,
      "probability": 0.95,
      "expectedDropPct": -30.31,
      "features": {
        "velocity3h": -30.31,
        "acceleration": -1.0,
        "dropFrequency": 1.0,
        "consecutiveDrops": 2,
        "maxSingleDropPct": 96.06,
        "marketPressure": 0.0,
        "totalScans": 3,
        "totalDrops": 2
      },
      "daysToCheckin": 96
    },
    {
      "detailId": 39006,
      "hotelId": 20702,
      "hotelName": "Embassy Suites by Hilton Miami International Airport",
      "category": "Suite",
      "board": "Ro",
      "currentPrice": 460.37,
      "signal": "STRONG_PUT",
      "strength": 9,
      "probability": 0.95,
      "expectedDropPct": -30.31,
      "features": {
        "velocity3h": -30.31,
        "acceleration": -1.0,
        "dropFrequency": 1.0,
        "consecutiveDrops": 2,
        "maxSingleDropPct": 60.84,
        "marketPressure": 0.0,
        "totalScans": 3,
        "totalDrops": 2
      },
      "daysToCheckin": 96
    },
    {
      "detailId": 38961,
      "hotelId": 20702,
      "hotelName": "Embassy Suites by Hilton Miami International Airport",
      "category": "Suite",
      "board": "Ro",
      "currentPrice": 740.46,
      "signal": "STRONG_PUT",
      "strength": 9,
      "probability": 0.95,
      "expectedDropPct": -30.31,
      "features": {
        "velocity3h": -30.31,
        "acceleration": -1.0,
        "dropFrequency": 1.0,
        "consecutiveDrops": 2,
        "maxSingleDropPct": 37.83,
        "marketPressure": 0.0,
        "totalScans": 3,
        "totalDrops": 2
      },
      "daysToCheckin": 96
    },
    {
      "detailId": 39005,
      "hotelId": 20702,
      "hotelName": "Embassy Suites by Hilton Miami International Airport",
      "category": "Suite",
      "board": "Ro",
      "currentPrice": 353.23,
      "signal": "STRONG_PUT",
      "strength": 9,
      "probability": 0.95,
      "expectedDropPct": -25.76,
      "features": {
        "velocity3h": -25.76,
        "acceleration": -1.0,
        "dropFrequency": 1.0,
        "consecutiveDrops": 2,
        "maxSingleDropPct": 106.04,
        "marketPressure": 0.0,
        "totalScans": 3,
        "totalDrops": 2
      },
      "daysToCheckin": 90
    },
    {
      "detailId": 38983,
      "hotelId": 20702,
      "hotelName": "Embassy Suites by Hilton Miami International Airport",
      "category": "Suite",
      "board": "Ro",
      "currentPrice": 727.8,
      "signal": "STRONG_PUT",
      "strength": 9,
      "probability": 0.95,
      "expectedDropPct": -25.76,
      "features": {
        "velocity3h": -25.76,
        "acceleration": -1.0,
        "dropFrequency": 1.0,
        "consecutiveDrops": 2,
        "maxSingleDropPct": 51.47,
        "marketPressure": 0.0,
        "totalScans": 3,
        "totalDrops": 2
      },
      "daysToCheckin": 90
    },
    {
      "detailId": 38956,
      "hotelId": 20702,
      "hotelName": "Embassy Suites by Hilton Miami International Airport",
      "category": "Suite",
      "board": "Ro",
      "currentPrice": 728.65,
      "signal": "STRONG_PUT",
      "strength": 9,
      "probability": 0.95,
      "expectedDropPct": -25.76,
      "features": {
        "velocity3h": -25.76,
        "acceleration": -1.0,
        "dropFrequency": 1.0,
        "consecutiveDrops": 2,
        "maxSingleDropPct": 51.41,
        "marketPressure": 0.0,
        "totalScans": 3,
        "totalDrops": 2
      },
      "daysToCheckin": 90
    },
    {
      "detailId": 39843,
      "hotelId": 20702,
      "hotelName": "Embassy Suites by Hilton Miami International Airport",
      "category": "Suite",
      "board": "Ro",
      "currentPrice": 233.95,
      "signal": "STRONG_PUT",
      "strength": 9,
      "probability": 0.95,
      "expectedDropPct": -22.78,
      "features": {
        "velocity3h": -22.78,
        "acceleration": -1.0,
        "dropFrequency": 1.0,
        "consecutiveDrops": 2,
        "maxSingleDropPct": 82.95,
        "marketPressure": 0.0,
        "totalScans": 3,
        "totalDrops": 2
      },
      "daysToCheckin": 68
    },
    {
      "detailId": 39773,
      "hotelId": 20702,
      "hotelName": "Embassy Suites by Hilton Miami International Airport",
      "category": "Suite",
      "board": "Ro",
      "currentPrice": 428.01,
      "signal": "STRONG_PUT",
      "strength": 9,
      "probability": 0.95,
      "expectedDropPct": -22.78,
      "features": {
        "velocity3h": -22.78,
        "acceleration": -1.0,
        "dropFrequency": 1.0,
        "consecutiveDrops": 2,
        "maxSingleDropPct": 45.34,
        "marketPressure": 0.0,
        "totalScans": 3,
        "totalDrops": 2
      },
      "daysToCheckin": 68
    },
    {
      "detailId": 38916,
      "hotelId": 20702,
      "hotelName": "Embassy Suites by Hilton Miami International Airport",
      "category": "Suite",
      "board": "Ro",
      "currentPrice": 429.74,
      "signal": "STRONG_PUT",
      "strength": 9,
      "probability": 0.95,
      "expectedDropPct": -22.78,
      "features": {
        "velocity3h": -22.78,
        "acceleration": -1.0,
        "dropFrequency": 1.0,
        "consecutiveDrops": 2,
        "maxSingleDropPct": 45.16,
        "marketPressure": 0.0,
        "totalScans": 3,
        "totalDrops": 2
      },
      "daysToCheckin": 68
    },
    {
      "detailId": 39815,
      "hotelId": 24982,
      "hotelName": "Hilton Miami Downtown",
      "category": "Suite",
      "board": "Ro",
      "currentPrice": 254.53,
      "signal": "STRONG_PUT",
      "strength": 9,
      "probability": 0.95,
      "expectedDropPct": -17.27,
      "features": {
        "velocity3h": -17.267,
        "acceleration": -1.0,
        "dropFrequency": 0.667,
        "consecutiveDrops": 2,
        "maxSingleDropPct": 223.61,
        "marketPressure": 0.0,
        "totalScans": 5,
        "totalDrops": 2
      },
      "daysToCheckin": 94
    },
    {
      "detailId": 39030,
      "hotelId": 24982,
      "hotelName": "Hilton Miami Downtown",
      "category": "Suite",
      "board": "Ro",
      "currentPrice": 822.94,
      "signal": "STRONG_PUT",
      "strength": 9,
      "probability": 0.95,
      "expectedDropPct": -17.27,
      "features": {
        "velocity3h": -17.267,
        "acceleration": -1.0,
        "dropFrequency": 0.667,
        "consecutiveDrops": 2,
        "maxSingleDropPct": 69.16,
        "marketPressure": 0.0,
        "totalScans": 5,
        "totalDrops": 2
      },
      "daysToCheckin": 94
    },
    {
      "detailId": 39077,
      "hotelId": 24982,
      "hotelName": "Hilton Miami Downtown",
      "category": "Suite",
      "board": "Ro",
      "currentPrice": 824.05,
      "signal": "STRONG_PUT",
      "strength": 9,
      "probability": 0.95,
      "expectedDropPct": -17.27,
      "features": {
        "velocity3h": -17.267,
        "acceleration": -1.0,
        "dropFrequency": 0.667,
        "consecutiveDrops": 2,
        "maxSingleDropPct": 69.07,
        "marketPressure": 0.0,
        "totalScans": 5,
        "totalDrops": 2
      },
      "daysToCheckin": 94
    },
    {
      "detailId": 39349,
      "hotelId": 24982,
      "hotelName": "Hilton Miami Downtown",
      "category": "Suite",
      "board": "Ro",
      "currentPrice": 823.68,
      "signal": "STRONG_PUT",
      "strength": 9,
      "probability": 0.95,
      "expectedDropPct": -17.27,
      "features": {
        "velocity3h": -17.267,
        "acceleration": -1.0,
        "dropFrequency": 0.667,
        "consecutiveDrops": 2,
        "maxSingleDropPct": 69.1,
        "marketPressure": 0.0,
        "totalScans": 5,
        "totalDrops": 2
      },
      "daysToCheckin": 94
    },
    {
      "detailId": 39415,
      "hotelId": 24982,
      "hotelName": "Hilton Miami Downtown",
      "category": "Suite",
      "board": "Ro",
      "currentPrice": 823.68,
      "signal": "STRONG_PUT",
      "strength": 9,
      "probability": 0.95,
      "expectedDropPct": -17.27,
      "features": {
        "velocity3h": -17.267,
        "acceleration": -1.0,
        "dropFrequency": 0.667,
        "consecutiveDrops": 2,
        "maxSingleDropPct": 69.1,
        "marketPressure": 0.0,
        "totalScans": 5,
        "totalDrops": 2
      },
      "daysToCheckin": 94
    },
    {
      "detailId": 41909,
      "hotelId": 24982,
      "hotelName": "Hilton Miami Downtown",
      "category": "Suite",
      "board": "Ro",
      "currentPrice": 345.63,
      "signal": "STRONG_PUT",
      "strength": 9,
      "probability": 0.95,
      "expectedDropPct": -17.05,
      "features": {
        "velocity3h": -17.055,
        "acceleration": -1.0,
        "dropFrequency": 1.0,
        "consecutiveDrops": 2,
        "maxSingleDropPct": 36.33,
        "marketPressure": 0.0,
        "totalScans": 3,
        "totalDrops": 2
      },
      "daysToCheckin": 65
    },
    {
      "detailId": 39210,
      "hotelId": 24982,
      "hotelName": "Hilton Miami Downtown",
      "category": "Suite",
      "board": "Ro",
      "currentPrice": 398.94,
      "signal": "STRONG_PUT",
      "strength": 9,
      "probability": 0.95,
      "expectedDropPct": -17.05,
      "features": {
        "velocity3h": -17.055,
        "acceleration": -1.0,
        "dropFrequency": 1.0,
        "consecutiveDrops": 2,
        "maxSingleDropPct": 31.48,
        "marketPressure": 0.0,
        "totalScans": 3,
        "totalDrops": 2
      },
      "daysToCheckin": 65
    },
    {
      "detailId": 39045,
      "hotelId": 24982,
      "hotelName": "Hilton Miami Downtown",
      "category": "Suite",
      "board": "Ro",
      "currentPrice": 524.52,
      "signal": "STRONG_PUT",
      "strength": 9,
      "probability": 0.95,
      "expectedDropPct": -17.05,
      "features": {
        "velocity3h": -17.055,
        "acceleration": -1.0,
        "dropFrequency": 1.0,
        "consecutiveDrops": 2,
        "maxSingleDropPct": 23.94,
        "marketPressure": 0.0,
        "totalScans": 3,
        "totalDrops": 2
      },
      "daysToCheckin": 65
    },
    {
      "detailId": 41889,
      "hotelId": 852120,
      "hotelName": "SLS LUX Brickell",
      "category": "Suite",
      "board": "Ro",
      "currentPrice": 685.09,
      "signal": "STRONG_PUT",
      "strength": 9,
      "probability": 0.95,
      "expectedDropPct": -13.69,
      "features": {
        "velocity3h": -13.685,
        "acceleration": -1.0,
        "dropFrequency": 1.0,
        "consecutiveDrops": 2,
        "maxSingleDropPct": 36.6,
        "marketPressure": 0.0,
        "totalScans": 3,
        "totalDrops": 2
      },
      "daysToCheckin": 44
    },
    {
      "detailId": 41608,
      "hotelId": 852120,
      "hotelName": "SLS LUX Brickell",
      "category": "Suite",
      "board": "Ro",
      "currentPrice": 935.8,
      "signal": "STRONG_PUT",
      "strength": 9,
      "probability": 0.95,
      "expectedDropPct": -13.69,
      "features": {
        "velocity3h": -13.685,
        "acceleration": -1.0,
        "dropFrequency": 1.0,
        "consecutiveDrops": 2,
        "maxSingleDropPct": 26.79,
        "marketPressure": 0.0,
        "totalScans": 3,
        "totalDrops": 2
      },
      "daysToCheckin": 44
    },
    {
      "detailId": 41455,
      "hotelId": 852120,
      "hotelName": "SLS LUX Brickell",
      "category": "Suite",
      "board": "Ro",
      "currentPrice": 943.31,
      "signal": "STRONG_PUT",
      "strength": 9,
      "probability": 0.95,
      "expectedDropPct": -13.69,
      "features": {
        "velocity3h": -13.685,
        "acceleration": -1.0,
        "dropFrequency": 1.0,
        "consecutiveDrops": 2,
        "maxSingleDropPct": 26.58,
        "marketPressure": 0.0,
        "totalScans": 3,
        "totalDrops": 2
      },
      "daysToCheckin": 44
    },
    {
      "detailId": 41910,
      "hotelId": 24982,
      "hotelName": "Hilton Miami Downtown",
      "category": "Standard",
      "board": "Ro",
      "currentPrice": 283.95,
      "signal": "STRONG_PUT",
      "strength": 9,
      "probability": 0.95,
      "expectedDropPct": -12.81,
      "features": {
        "velocity3h": -12.81,
        "acceleration": -1.0,
        "dropFrequency": 1.0,
        "consecutiveDrops": 3,
        "maxSingleDropPct": 27.64,
        "marketPressure": 0.0,
        "totalScans": 4,
        "totalDrops": 3
      },
      "daysToCheckin": 65
    },
    {
      "detailId": 39770,
      "hotelId": 24982,
      "hotelName": "Hilton Miami Downtown",
      "category": "Standard",
      "board": "Ro",
      "currentPrice": 362.43,
      "signal": "STRONG_PUT",
      "strength": 9,
      "probability": 0.95,
      "expectedDropPct": -12.81,
      "features": {
        "velocity3h": -12.81,
        "acceleration": -1.0,
        "dropFrequency": 1.0,
        "consecutiveDrops": 3,
        "maxSingleDropPct": 21.65,
        "marketPressure": 0.0,
        "totalScans": 4,
        "totalDrops": 3
      },
      "daysToCheckin": 65
    },
    {
      "detailId": 39211,
      "hotelId": 24982,
      "hotelName": "Hilton Miami Downtown",
      "category": "Standard",
      "board": "Ro",
      "currentPrice": 392.55,
      "signal": "STRONG_PUT",
      "strength": 9,
      "probability": 0.95,
      "expectedDropPct": -12.81,
      "features": {
        "velocity3h": -12.81,
        "acceleration": -1.0,
        "dropFrequency": 1.0,
        "consecutiveDrops": 3,
        "maxSingleDropPct": 19.99,
        "marketPressure": 0.0,
        "totalScans": 4,
        "totalDrops": 3
      },
      "daysToCheckin": 65
    },
    {
      "detailId": 39044,
      "hotelId": 24982,
      "hotelName": "Hilton Miami Downtown",
      "category": "Standard",
      "board": "Ro",
      "currentPrice": 461.15,
      "signal": "STRONG_PUT",
      "strength": 9,
      "probability": 0.95,
      "expectedDropPct": -12.81,
      "features": {
        "velocity3h": -12.81,
        "acceleration": -1.0,
        "dropFrequency": 1.0,
        "consecutiveDrops": 3,
        "maxSingleDropPct": 17.02,
        "marketPressure": 0.0,
        "totalScans": 4,
        "totalDrops": 3
      },
      "daysToCheckin": 65
    },
    {
      "detailId": 40724,
      "hotelId": 20702,
      "hotelName": "Embassy Suites by Hilton Miami International Airport",
      "category": "Suite",
      "board": "Ro",
      "currentPrice": 337.96,
      "signal": "STRONG_PUT",
      "strength": 9,
      "probability": 0.95,
      "expectedDropPct": -10.8,
      "features": {
        "velocity3h": -10.797,
        "acceleration": -1.0,
        "dropFrequency": 0.667,
        "consecutiveDrops": 2,
        "maxSingleDropPct": 45.93,
        "marketPressure": 0.0,
        "totalScans": 4,
        "totalDrops": 2
      },
      "daysToCheckin": 93
    },
    {
      "detailId": 39019,
      "hotelId": 20702,
      "hotelName": "Embassy Suites by Hilton Miami International Airport",
      "category": "Suite",
      "board": "Ro",
      "currentPrice": 492.08,
      "signal": "STRONG_PUT",
      "strength": 9,
      "probability": 0.95,
      "expectedDropPct": -10.8,
      "features": {
        "velocity3h": -10.797,
        "acceleration": -1.0,
        "dropFrequency": 0.667,
        "consecutiveDrops": 2,
        "maxSingleDropPct": 31.55,
        "marketPressure": 0.0,
        "totalScans": 4,
        "totalDrops": 2
      },
      "daysToCheckin": 93
    },
    {
      "detailId": 39919,
      "hotelId": 20702,
      "hotelName": "Embassy Suites by Hilton Miami International Airport",
      "category": "Suite",
      "board": "Ro",
      "currentPrice": 493.2,
      "signal": "STRONG_PUT",
      "strength": 9,
      "probability": 0.95,
      "expectedDropPct": -10.8,
      "features": {
        "velocity3h": -10.797,
        "acceleration": -1.0,
        "dropFrequency": 0.667,
        "consecutiveDrops": 2,
        "maxSingleDropPct": 31.48,
        "marketPressure": 0.0,
        "totalScans": 4,
        "totalDrops": 2
      },
      "daysToCheckin": 93
    },
    {
      "detailId": 38959,
      "hotelId": 20702,
      "hotelName": "Embassy Suites by Hilton Miami International Airport",
      "category": "Suite",
      "board": "Ro",
      "currentPrice": 499.86,
      "signal": "STRONG_PUT",
      "strength": 9,
      "probability": 0.95,
      "expectedDropPct": -10.8,
      "features": {
        "velocity3h": -10.797,
        "acceleration": -1.0,
        "dropFrequency": 0.667,
        "consecutiveDrops": 2,
        "maxSingleDropPct": 31.06,
        "marketPressure": 0.0,
        "totalScans": 4,
        "totalDrops": 2
      },
      "daysToCheckin": 93
    },
    {
      "detailId": 40745,
      "hotelId": 66814,
      "hotelName": "Breakwater South Beach",
      "category": "Superior",
      "board": "Ro",
      "currentPrice": 180.9,
      "signal": "STRONG_PUT",
      "strength": 9,
      "probability": 0.95,
      "expectedDropPct": -10.07,
      "features": {
        "velocity3h": -10.07,
        "acceleration": -1.0,
        "dropFrequency": 0.75,
        "consecutiveDrops": 3,
        "maxSingleDropPct": 51.21,
        "marketPressure": 0.0,
        "totalScans": 5,
        "totalDrops": 3
      },
      "daysToCheckin": 85
    },
    {
      "detailId": 39810,
      "hotelId": 66814,
      "hotelName": "Breakwater South Beach",
      "category": "Superior",
      "board": "Ro",
      "currentPrice": 205.5,
      "signal": "STRONG_PUT",
      "strength": 9,
      "probability": 0.95,
      "expectedDropPct": -10.07,
      "features": {
        "velocity3h": -10.07,
        "acceleration": -1.0,
        "dropFrequency": 0.75,
        "consecutiveDrops": 3,
        "maxSingleDropPct": 45.08,
        "marketPressure": 0.0,
        "totalScans": 5,
        "totalDrops": 3
      },
      "daysToCheckin": 85
    },
    {
      "detailId": 39529,
      "hotelId": 66814,
      "hotelName": "Breakwater South Beach",
      "category": "Superior",
      "board": "Ro",
      "currentPrice": 210.3,
      "signal": "STRONG_PUT",
      "strength": 9,
      "probability": 0.95,
      "expectedDropPct": -10.07,
      "features": {
        "velocity3h": -10.07,
        "acceleration": -1.0,
        "dropFrequency": 0.75,
        "consecutiveDrops": 3,
        "maxSingleDropPct": 44.05,
        "marketPressure": 0.0,
        "totalScans": 5,
        "totalDrops": 3
      },
      "daysToCheckin": 85
    },
    {
      "detailId": 39797,
      "hotelId": 66814,
      "hotelName": "Breakwater South Beach",
      "category": "Superior",
      "board": "Ro",
      "currentPrice": 211.99,
      "signal": "STRONG_PUT",
      "strength": 9,
      "probability": 0.95,
      "expectedDropPct": -10.07,
      "features": {
        "velocity3h": -10.07,
        "acceleration": -1.0,
        "dropFrequency": 0.75,
        "consecutiveDrops": 3,
        "maxSingleDropPct": 43.7,
        "marketPressure": 0.0,
        "totalScans": 5,
        "totalDrops": 3
      },
      "daysToCheckin": 85
    },
    {
      "detailId": 39447,
      "hotelId": 66814,
      "hotelName": "Breakwater South Beach",
      "category": "Superior",
      "board": "Ro",
      "currentPrice": 302.93,
      "signal": "STRONG_PUT",
      "strength": 9,
      "probability": 0.95,
      "expectedDropPct": -10.07,
      "features": {
        "velocity3h": -10.07,
        "acceleration": -1.0,
        "dropFrequency": 0.75,
        "consecutiveDrops": 3,
        "maxSingleDropPct": 30.58,
        "marketPressure": 0.0,
        "totalScans": 5,
        "totalDrops": 3
      },
      "daysToCheckin": 85
    },
    {
      "detailId": 39614,
      "hotelId": 66814,
      "hotelName": "Breakwater South Beach",
      "category": "Superior",
      "board": "Ro",
      "currentPrice": 175.99,
      "signal": "STRONG_PUT",
      "strength": 9,
      "probability": 0.95,
      "expectedDropPct": -9.92,
      "features": {
        "velocity3h": -9.922,
        "acceleration": -1.0,
        "dropFrequency": 0.75,
        "consecutiveDrops": 3,
        "maxSingleDropPct": 65.2,
        "marketPressure": 0.0,
        "totalScans": 5,
        "totalDrops": 3
      },
      "daysToCheckin": 78
    },
    {
      "detailId": 39390,
      "hotelId": 66814,
      "hotelName": "Breakwater South Beach",
      "category": "Superior",
      "board": "Ro",
      "currentPrice": 218.85,
      "signal": "STRONG_PUT",
      "strength": 9,
      "probability": 0.95,
      "expectedDropPct": -9.92,
      "features": {
        "velocity3h": -9.922,
        "acceleration": -1.0,
        "dropFrequency": 0.75,
        "consecutiveDrops": 3,
        "maxSingleDropPct": 52.43,
        "marketPressure": 0.0,
        "totalScans": 5,
        "totalDrops": 3
      },
      "daysToCheckin": 78
    },
    {
      "detailId": 39584,
      "hotelId": 66814,
      "hotelName": "Breakwater South Beach",
      "category": "Superior",
      "board": "Ro",
      "currentPrice": 290.73,
      "signal": "STRONG_PUT",
      "strength": 9,
      "probability": 0.95,
      "expectedDropPct": -9.92,
      "features": {
        "velocity3h": -9.922,
        "acceleration": -1.0,
        "dropFrequency": 0.75,
        "consecutiveDrops": 3,
        "maxSingleDropPct": 39.47,
        "marketPressure": 0.0,
        "totalScans": 5,
        "totalDrops": 3
      },
      "daysToCheckin": 78
    },
    {
      "detailId": 39204,
      "hotelId": 66814,
      "hotelName": "Breakwater South Beach",
      "category": "Superior",
      "board": "Ro",
      "currentPrice": 291.8,
      "signal": "STRONG_PUT",
      "strength": 9,
      "probability": 0.95,
      "expectedDropPct": -9.92,
      "features": {
        "velocity3h": -9.922,
        "acceleration": -1.0,
        "dropFrequency": 0.75,
        "consecutiveDrops": 3,
        "maxSingleDropPct": 39.32,
        "marketPressure": 0.0,
        "totalScans": 5,
        "totalDrops": 3
      },
      "daysToCheckin": 78
    },
    {
      "detailId": 39545,
      "hotelId": 66814,
      "hotelName": "Breakwater South Beach",
      "category": "Superior",
      "board": "Ro",
      "currentPrice": 291.91,
      "signal": "STRONG_PUT",
      "strength": 9,
      "probability": 0.95,
      "expectedDropPct": -9.92,
      "features": {
        "velocity3h": -9.922,
        "acceleration": -1.0,
        "dropFrequency": 0.75,
        "consecutiveDrops": 3,
        "maxSingleDropPct": 39.31,
        "marketPressure": 0.0,
        "totalScans": 5,
        "totalDrops": 3
      },
      "daysToCheckin": 78
    },
    {
      "detailId": 39094,
      "hotelId": 24982,
      "hotelName": "Hilton Miami Downtown",
      "category": "Suite",
      "board": "Ro",
      "currentPrice": 484.62,
      "signal": "STRONG_PUT",
      "strength": 9,
      "probability": 0.95,
      "expectedDropPct": -7.8,
      "features": {
        "velocity3h": -7.805,
        "acceleration": -1.0,
        "dropFrequency": 1.0,
        "consecutiveDrops": 2,
        "maxSingleDropPct": 15.6,
        "marketPressure": 0.0,
        "totalScans": 3,
        "totalDrops": 2
      },
      "daysToCheckin": 36
    },
    {
      "detailId": 39344,
      "hotelId": 24982,
      "hotelName": "Hilton Miami Downtown",
      "category": "Suite",
      "board": "Ro",
      "currentPrice": 484.58,
      "signal": "STRONG_PUT",
      "strength": 9,
      "probability": 0.95,
      "expectedDropPct": -7.8,
      "features": {
        "velocity3h": -7.805,
        "acceleration": -1.0,
        "dropFrequency": 1.0,
        "consecutiveDrops": 2,
        "maxSingleDropPct": 15.6,
        "marketPressure": 0.0,
        "totalScans": 3,
        "totalDrops": 2
      },
      "daysToCheckin": 36
    },
    {
      "detailId": 41482,
      "hotelId": 852120,
      "hotelName": "SLS LUX Brickell",
      "category": "Suite",
      "board": "Ro",
      "currentPrice": 604.09,
      "signal": "STRONG_PUT",
      "strength": 9,
      "probability": 0.95,
      "expectedDropPct": -6.91,
      "features": {
        "velocity3h": -6.91,
        "acceleration": -1.0,
        "dropFrequency": 1.0,
        "consecutiveDrops": 2,
        "maxSingleDropPct": 13.03,
        "marketPressure": 0.0,
        "totalScans": 3,
        "totalDrops": 2
      },
      "daysToCheckin": 77
    },
    {
      "detailId": 41625,
      "hotelId": 852120,
      "hotelName": "SLS LUX Brickell",
      "category": "Suite",
      "board": "Ro",
      "currentPrice": 599.28,
      "signal": "STRONG_PUT",
      "strength": 9,
      "probability": 0.95,
      "expectedDropPct": -6.91,
      "features": {
        "velocity3h": -6.91,
        "acceleration": -1.0,
        "dropFrequency": 1.0,
        "consecutiveDrops": 2,
        "maxSingleDropPct": 13.13,
        "marketPressure": 0.0,
        "totalScans": 3,
        "totalDrops": 2
      },
      "daysToCheckin": 77
    },
    {
      "detailId": 41971,
      "hotelId": 852120,
      "hotelName": "SLS LUX Brickell",
      "category": "Suite",
      "board": "Ro",
      "currentPrice": 520.58,
      "signal": "STRONG_PUT",
      "strength": 9,
      "probability": 0.95,
      "expectedDropPct": -6.91,
      "features": {
        "velocity3h": -6.91,
        "acceleration": -1.0,
        "dropFrequency": 1.0,
        "consecutiveDrops": 2,
        "maxSingleDropPct": 15.12,
        "marketPressure": 0.0,
        "totalScans": 3,
        "totalDrops": 2
      },
      "daysToCheckin": 77
    },
    {
      "detailId": 41982,
      "hotelId": 852120,
      "hotelName": "SLS LUX Brickell",
      "category": "Suite",
      "board": "Ro",
      "currentPrice": 520.58,
      "signal": "STRONG_PUT",
      "strength": 9,
      "probability": 0.95,
      "expectedDropPct": -6.85,
      "features": {
        "velocity3h": -6.85,
        "acceleration": -1.0,
        "dropFrequency": 1.0,
        "consecutiveDrops": 2,
        "maxSingleDropPct": 12.9,
        "marketPressure": 0.0,
        "totalScans": 3,
        "totalDrops": 2
      },
      "daysToCheckin": 85
    },
    {
      "detailId": 41632,
      "hotelId": 852120,
      "hotelName": "SLS LUX Brickell",
      "category": "Suite",
      "board": "Ro",
      "currentPrice": 587.76,
      "signal": "STRONG_PUT",
      "strength": 9,
      "probability": 0.95,
      "expectedDropPct": -6.85,
      "features": {
        "velocity3h": -6.85,
        "acceleration": -1.0,
        "dropFrequency": 1.0,
        "consecutiveDrops": 2,
        "maxSingleDropPct": 11.43,
        "marketPressure": 0.0,
        "totalScans": 3,
        "totalDrops": 2
      },
      "daysToCheckin": 85
    },
    {
      "detailId": 41495,
      "hotelId": 852120,
      "hotelName": "SLS LUX Brickell",
      "category": "Suite",
      "board": "Ro",
      "currentPrice": 603.23,
      "signal": "STRONG_PUT",
      "strength": 9,
      "probability": 0.95,
      "expectedDropPct": -6.85,
      "features": {
        "velocity3h": -6.85,
        "acceleration": -1.0,
        "dropFrequency": 1.0,
        "consecutiveDrops": 2,
        "maxSingleDropPct": 11.14,
        "marketPressure": 0.0,
        "totalScans": 3,
        "totalDrops": 2
      },
      "daysToCheckin": 85
    },
    {
      "detailId": 41532,
      "hotelId": 852120,
      "hotelName": "SLS LUX Brickell",
      "category": "Suite",
      "board": "Ro",
      "currentPrice": 602.37,
      "signal": "STRONG_PUT",
      "strength": 9,
      "probability": 0.95,
      "expectedDropPct": -6.79,
      "features": {
        "velocity3h": -6.79,
        "acceleration": -1.0,
        "dropFrequency": 1.0,
        "consecutiveDrops": 2,
        "maxSingleDropPct": 13.07,
        "marketPressure": 0.0,
        "totalScans": 3,
        "totalDrops": 2
      },
      "daysToCheckin": 78
    },
    {
      "detailId": 41626,
      "hotelId": 852120,
      "hotelName": "SLS LUX Brickell",
      "category": "Suite",
      "board": "Ro",
      "currentPrice": 599.28,
      "signal": "STRONG_PUT",
      "strength": 9,
      "probability": 0.95,
      "expectedDropPct": -6.79,
      "features": {
        "velocity3h": -6.79,
        "acceleration": -1.0,
        "dropFrequency": 1.0,
        "consecutiveDrops": 2,
        "maxSingleDropPct": 13.13,
        "marketPressure": 0.0,
        "totalScans": 3,
        "totalDrops": 2
      },
      "daysToCheckin": 78
    },
    {
      "detailId": 41972,
      "hotelId": 852120,
      "hotelName": "SLS LUX Brickell",
      "category": "Suite",
      "board": "Ro",
      "currentPrice": 520.58,
      "signal": "STRONG_PUT",
      "strength": 9,
      "probability": 0.95,
      "expectedDropPct": -6.79,
      "features": {
        "velocity3h": -6.79,
        "acceleration": -1.0,
        "dropFrequency": 1.0,
        "consecutiveDrops": 2,
        "maxSingleDropPct": 15.12,
        "marketPressure": 0.0,
        "totalScans": 3,
        "totalDrops": 2
      },
      "daysToCheckin": 78
    },
    {
      "detailId": 42082,
      "hotelId": 20702,
      "hotelName": "Embassy Suites by Hilton Miami International Airport",
      "category": "Suite",
      "board": "Bb",
      "currentPrice": 443.15,
      "signal": "STRONG_PUT",
      "strength": 9,
      "probability": 0.95,
      "expectedDropPct": -6.47,
      "features": {
        "velocity3h": -6.475,
        "acceleration": -1.0,
        "dropFrequency": 1.0,
        "consecutiveDrops": 1,
        "maxSingleDropPct": 14.88,
        "marketPressure": -0.3054,
        "totalScans": 3,
        "totalDrops": 1
      },
      "daysToCheckin": 46
    },
    {
      "detailId": 41892,
      "hotelId": 852120,
      "hotelName": "SLS LUX Brickell",
      "category": "Suite",
      "board": "Ro",
      "currentPrice": 558.52,
      "signal": "STRONG_PUT",
      "strength": 9,
      "probability": 0.95,
      "expectedDropPct": -6.15,
      "features": {
        "velocity3h": -6.15,
        "acceleration": -1.0,
        "dropFrequency": 0.667,
        "consecutiveDrops": 2,
        "maxSingleDropPct": 22.67,
        "marketPressure": 0.0,
        "totalScans": 4,
        "totalDrops": 2
      },
      "daysToCheckin": 81
    },
    {
      "detailId": 41629,
      "hotelId": 852120,
      "hotelName": "SLS LUX Brickell",
      "category": "Suite",
      "board": "Ro",
      "currentPrice": 682.25,
      "signal": "STRONG_PUT",
      "strength": 9,
      "probability": 0.95,
      "expectedDropPct": -6.15,
      "features": {
        "velocity3h": -6.15,
        "acceleration": -1.0,
        "dropFrequency": 0.667,
        "consecutiveDrops": 2,
        "maxSingleDropPct": 18.56,
        "marketPressure": 0.0,
        "totalScans": 4,
        "totalDrops": 2
      },
      "daysToCheckin": 81
    },
    {
      "detailId": 41487,
      "hotelId": 852120,
      "hotelName": "SLS LUX Brickell",
      "category": "Suite",
      "board": "Ro",
      "currentPrice": 684.85,
      "signal": "STRONG_PUT",
      "strength": 9,
      "probability": 0.95,
      "expectedDropPct": -6.15,
      "features": {
        "velocity3h": -6.15,
        "acceleration": -1.0,
        "dropFrequency": 0.667,
        "consecutiveDrops": 2,
        "maxSingleDropPct": 18.49,
        "marketPressure": 0.0,
        "totalScans": 4,
        "totalDrops": 2
      },
      "daysToCheckin": 81
    },
    {
      "detailId": 41763,
      "hotelId": 852120,
      "hotelName": "SLS LUX Brickell",
      "category": "Suite",
      "board": "Ro",
      "currentPrice": 685.12,
      "signal": "STRONG_PUT",
      "strength": 9,
      "probability": 0.95,
      "expectedDropPct": -6.15,
      "features": {
        "velocity3h": -6.15,
        "acceleration": -1.0,
        "dropFrequency": 0.667,
        "consecutiveDrops": 2,
        "maxSingleDropPct": 18.48,
        "marketPressure": 0.0,
        "totalScans": 4,
        "totalDrops": 2
      },
      "daysToCheckin": 81
    },
    {
      "detailId": 39603,
      "hotelId": 66814,
      "hotelName": "Breakwater South Beach",
      "category": "Deluxe",
      "board": "Ro",
      "currentPrice": 258.16,
      "signal": "STRONG_PUT",
      "strength": 9,
      "probability": 0.95,
      "expectedDropPct": -6.13,
      "features": {
        "velocity3h": -6.13,
        "acceleration": -1.0,
        "dropFrequency": 1.0,
        "consecutiveDrops": 2,
        "maxSingleDropPct": 13.77,
        "marketPressure": 0.0,
        "totalScans": 3,
        "totalDrops": 2
      },
      "daysToCheckin": 41
    },
    {
      "detailId": 39517,
      "hotelId": 66814,
      "hotelName": "Breakwater South Beach",
      "category": "Deluxe",
      "board": "Ro",
      "currentPrice": 293.71,
      "signal": "STRONG_PUT",
      "strength": 9,
      "probability": 0.95,
      "expectedDropPct": -6.13,
      "features": {
        "velocity3h": -6.13,
        "acceleration": -1.0,
        "dropFrequency": 1.0,
        "consecutiveDrops": 2,
        "maxSingleDropPct": 12.1,
        "marketPressure": 0.0,
        "totalScans": 3,
        "totalDrops": 2
      },
      "daysToCheckin": 41
    },
    {
      "detailId": 39461,
      "hotelId": 66814,
      "hotelName": "Breakwater South Beach",
      "category": "Deluxe",
      "board": "Ro",
      "currentPrice": 294.23,
      "signal": "STRONG_PUT",
      "strength": 9,
      "probability": 0.95,
      "expectedDropPct": -6.13,
      "features": {
        "velocity3h": -6.13,
        "acceleration": -1.0,
        "dropFrequency": 1.0,
        "consecutiveDrops": 2,
        "maxSingleDropPct": 12.08,
        "marketPressure": 0.0,
        "totalScans": 3,
        "totalDrops": 2
      },
      "daysToCheckin": 41
    },
    {
      "detailId": 41876,
      "hotelId": 66814,
      "hotelName": "Breakwater South Beach",
      "category": "Deluxe",
      "board": "Ro",
      "currentPrice": 219.19,
      "signal": "STRONG_PUT",
      "strength": 9,
      "probability": 0.95,
      "expectedDropPct": -5.01,
      "features": {
        "velocity3h": -5.01,
        "acceleration": -1.0,
        "dropFrequency": 0.667,
        "consecutiveDrops": 2,
        "maxSingleDropPct": 17.12,
        "marketPressure": 0.0,
        "totalScans": 4,
        "totalDrops": 2
      },
      "daysToCheckin": 55
    },
    {
      "detailId": 39524,
      "hotelId": 66814,
      "hotelName": "Breakwater South Beach",
      "category": "Deluxe",
      "board": "Ro",
      "currentPrice": 229.02,
      "signal": "STRONG_PUT",
      "strength": 9,
      "probability": 0.95,
      "expectedDropPct": -5.01,
      "features": {
        "velocity3h": -5.01,
        "acceleration": -1.0,
        "dropFrequency": 0.667,
        "consecutiveDrops": 2,
        "maxSingleDropPct": 16.39,
        "marketPressure": 0.0,
        "totalScans": 4,
        "totalDrops": 2
      },
      "daysToCheckin": 55
    },
    {
      "detailId": 41590,
      "hotelId": 66814,
      "hotelName": "Breakwater South Beach",
      "category": "Deluxe",
      "board": "Ro",
      "currentPrice": 256.72,
      "signal": "STRONG_PUT",
      "strength": 9,
      "probability": 0.95,
      "expectedDropPct": -5.01,
      "features": {
        "velocity3h": -5.01,
        "acceleration": -1.0,
        "dropFrequency": 0.667,
        "consecutiveDrops": 2,
        "maxSingleDropPct": 14.62,
        "marketPressure": 0.0,
        "totalScans": 4,
        "totalDrops": 2
      },
      "daysToCheckin": 55
    },
    {
      "detailId": 39407,
      "hotelId": 66814,
      "hotelName": "Breakwater South Beach",
      "category": "Deluxe",
      "board": "Ro",
      "currentPrice": 257.97,
      "signal": "STRONG_PUT",
      "strength": 9,
      "probability": 0.95,
      "expectedDropPct": -5.01,
      "features": {
        "velocity3h": -5.01,
        "acceleration": -1.0,
        "dropFrequency": 0.667,
        "consecutiveDrops": 2,
        "maxSingleDropPct": 14.55,
        "marketPressure": 0.0,
        "totalScans": 4,
        "totalDrops": 2
      },
      "daysToCheckin": 55
    },
    {
      "detailId": 40749,
      "hotelId": 66814,
      "hotelName": "Breakwater South Beach",
      "category": "Standard",
      "board": "Bb",
      "currentPrice": 462.9,
      "signal": "STRONG_PUT",
      "strength": 9,
      "probability": 0.9,
      "expectedDropPct": -95.51,
      "features": {
        "velocity3h": -95.51,
        "acceleration": -1.0,
        "dropFrequency": 1.0,
        "consecutiveDrops": 1,
        "maxSingleDropPct": 2129.11,
        "marketPressure": -0.2327,
        "totalScans": 2,
        "totalDrops": 1
      },
      "daysToCheckin": 94
    },
    {
      "detailId": 42978,
      "hotelId": 852120,
      "hotelName": "SLS LUX Brickell",
      "category": "Standard",
      "board": "Ro",
      "currentPrice": 2141.5,
      "signal": "STRONG_PUT",
      "strength": 9,
      "probability": 0.9,
      "expectedDropPct": -83.95,
      "features": {
        "velocity3h": -83.95,
        "acceleration": -1.0,
        "dropFrequency": 1.0,
        "consecutiveDrops": 1,
        "maxSingleDropPct": 523.08,
        "marketPressure": -0.1773,
        "totalScans": 2,
        "totalDrops": 1
      },
      "daysToCheckin": 87
    },
    {
      "detailId": 42238,
      "hotelId": 66814,
      "hotelName": "Breakwater South Beach",
      "category": "Standard",
      "board": "Bb",
      "currentPrice": 551.88,
      "signal": "STRONG_PUT",
      "strength": 9,
      "probability": 0.9,
      "expectedDropPct": -47.33,
      "features": {
        "velocity3h": -47.325,
        "acceleration": -1.0,
        "dropFrequency": 1.0,
        "consecutiveDrops": 2,
        "maxSingleDropPct": 1761.51,
        "marketPressure": 0.0,
        "totalScans": 3,
        "totalDrops": 2
      },
      "daysToCheckin": 93
    },
    {
      "detailId": 40748,
      "hotelId": 66814,
      "hotelName": "Breakwater South Beach",
      "category": "Standard",
      "board": "Bb",
      "currentPrice": 597.15,
      "signal": "STRONG_PUT",
      "strength": 9,
      "probability": 0.9,
      "expectedDropPct": -47.33,
      "features": {
        "velocity3h": -47.325,
        "acceleration": -1.0,
        "dropFrequency": 1.0,
        "consecutiveDrops": 2,
        "maxSingleDropPct": 1627.97,
        "marketPressure": 0.0,
        "totalScans": 3,
        "totalDrops": 2
      },
      "daysToCheckin": 93
    },
    {
      "detailId": 40439,
      "hotelId": 66814,
      "hotelName": "Breakwater South Beach",
      "category": "Standard",
      "board": "Bb",
      "currentPrice": 10318.56,
      "signal": "STRONG_PUT",
      "strength": 9,
      "probability": 0.9,
      "expectedDropPct": -47.33,
      "features": {
        "velocity3h": -47.325,
        "acceleration": -1.0,
        "dropFrequency": 1.0,
        "consecutiveDrops": 2,
        "maxSingleDropPct": 94.21,
        "marketPressure": 0.0,
        "totalScans": 3,
        "totalDrops": 2
      },
      "daysToCheckin": 93
    },
    {
      "detailId": 39889,
      "hotelId": 20702,
      "hotelName": "Embassy Suites by Hilton Miami International Airport",
      "category": "Standard",
      "board": "Ro",
      "currentPrice": 202.69,
      "signal": "STRONG_PUT",
      "strength": 9,
      "probability": 0.9,
      "expectedDropPct": -14.65,
      "features": {
        "velocity3h": -14.655,
        "acceleration": -1.0,
        "dropFrequency": 1.0,
        "consecutiveDrops": 2,
        "maxSingleDropPct": 40.9,
        "marketPressure": 0.0,
        "totalScans": 3,
        "totalDrops": 2
      },
      "daysToCheckin": 53
    },
    {
      "detailId": 39873,
      "hotelId": 20702,
      "hotelName": "Embassy Suites by Hilton Miami International Airport",
      "category": "Standard",
      "board": "Ro",
      "currentPrice": 285.6,
      "signal": "STRONG_PUT",
      "strength": 9,
      "probability": 0.9,
      "expectedDropPct": -14.65,
      "features": {
        "velocity3h": -14.655,
        "acceleration": -1.0,
        "dropFrequency": 1.0,
        "consecutiveDrops": 2,
        "maxSingleDropPct": 29.03,
        "marketPressure": 0.0,
        "totalScans": 3,
        "totalDrops": 2
      },
      "daysToCheckin": 53
    },
    {
      "detailId": 38998,
      "hotelId": 20702,
      "hotelName": "Embassy Suites by Hilton Miami International Airport",
      "category": "Standard",
      "board": "Ro",
      "currentPrice": 286.73,
      "signal": "STRONG_PUT",
      "strength": 9,
      "probability": 0.9,
      "expectedDropPct": -14.65,
      "features": {
        "velocity3h": -14.655,
        "acceleration": -1.0,
        "dropFrequency": 1.0,
        "consecutiveDrops": 2,
        "maxSingleDropPct": 28.92,
        "marketPressure": 0.0,
        "totalScans": 3,
        "totalDrops": 2
      },
      "daysToCheckin": 53
    },
    {
      "detailId": 39883,
      "hotelId": 20702,
      "hotelName": "Embassy Suites by Hilton Miami International Airport",
      "category": "Standard",
      "board": "Ro",
      "currentPrice": 187.94,
      "signal": "STRONG_PUT",
      "strength": 9,
      "probability": 0.9,
      "expectedDropPct": -12.44,
      "features": {
        "velocity3h": -12.44,
        "acceleration": -1.0,
        "dropFrequency": 1.0,
        "consecutiveDrops": 2,
        "maxSingleDropPct": 29.47,
        "marketPressure": 0.0,
        "totalScans": 3,
        "totalDrops": 2
      },
      "daysToCheckin": 34
    },
    {
      "detailId": 39187,
      "hotelId": 20702,
      "hotelName": "Embassy Suites by Hilton Miami International Airport",
      "category": "Standard",
      "board": "Ro",
      "currentPrice": 243.33,
      "signal": "STRONG_PUT",
      "strength": 9,
      "probability": 0.9,
      "expectedDropPct": -12.44,
      "features": {
        "velocity3h": -12.44,
        "acceleration": -1.0,
        "dropFrequency": 1.0,
        "consecutiveDrops": 2,
        "maxSingleDropPct": 22.76,
        "marketPressure": 0.0,
        "totalScans": 3,
        "totalDrops": 2
      },
      "daysToCheckin": 34
    },
    {
      "detailId": 38993,
      "hotelId": 20702,
      "hotelName": "Embassy Suites by Hilton Miami International Airport",
      "category": "Standard",
      "board": "Ro",
      "currentPrice": 250.18,
      "signal": "STRONG_PUT",
      "strength": 9,
      "probability": 0.9,
      "expectedDropPct": -12.44,
      "features": {
        "velocity3h": -12.44,
        "acceleration": -1.0,
        "dropFrequency": 1.0,
        "consecutiveDrops": 2,
        "maxSingleDropPct": 22.14,
        "marketPressure": 0.0,
        "totalScans": 3,
        "totalDrops": 2
      },
      "daysToCheckin": 34
    }
  ]
}